logprism-0.2.0.data/scripts/prism
prism/__init__.py
prism/colour.py
prism/config.py
prism/events.py
prism/grep.py
prism/log.py
prism/output.py
logprism-0.2.0.dist-info/LICENSE
logprism-0.2.0.dist-info/METADATA
logprism-0.2.0.dist-info/WHEEL
logprism-0.2.0.dist-info/top_level.txt
logprism-0.2.0.dist-info/RECORD
