Metadata-Version: 2.1
Name: logprism
Version: 0.2.0
Summary: Prism – Colourise log files (with ANSI characters codes)
Home-page: https://github.com/peterhil/prism
Author: Peter Hillerström
Author-email: peter.hillerstrom@gmail.com
License: BSD License
Classifier: Development Status :: 4 - Beta
Classifier: Environment :: Console
Classifier: Intended Audience :: Developers
Classifier: Intended Audience :: End Users/Desktop
Classifier: Intended Audience :: System Administrators
Classifier: License :: OSI Approved :: BSD License
Classifier: Operating System :: MacOS :: MacOS X
Classifier: Operating System :: POSIX
Classifier: Operating System :: Unix
Classifier: Programming Language :: Python
Classifier: Programming Language :: Python :: 2.7
Classifier: Programming Language :: Python :: 3
Classifier: Topic :: Software Development :: Bug Tracking
Classifier: Topic :: Software Development :: Quality Assurance
Classifier: Topic :: Software Development :: Testing
Classifier: Topic :: Internet :: Log Analysis
Classifier: Topic :: System :: Logging
Classifier: Topic :: System :: Monitoring
Classifier: Topic :: System :: Systems Administration
Classifier: Topic :: Text Processing :: Filters
Classifier: Topic :: Utilities
Requires: collections
License-File: LICENSE
Provides-Extra: test
Requires-Dist: pytest >=6.2.4 ; extra == 'test'
Provides-Extra: watchdog
Requires-Dist: watchdog >=2.1.2 ; extra == 'watchdog'
